{
  "currencies": {
    "USD": { "name": "United States Dollar" },
    "RUB": { "name": "Russian Ruble" },
    "PLN": { "name": "Polish Zloty" },
    "UAH": { "name": "Ukrainian Hryvnia" },
    "EUR": { "name": "Euro" }
  },
  "languages": {
    "uk": { "name": "Українська", "currency": "UAH" },
    "pl": { "name": "Polski", "currency": "PLN" },
    "en": { "name": "English", "currency": "USD" },
    "ru": { "name": "Русский", "currency": "RUB" }
  },
  "games": {
    "cs2": { "steam_id": 730, "dmarket_id": "a8db", "title": "Counter-Strike 2" },
    "dota2": { "steam_id": 570, "dmarket_id": "9a92", "title": "Dota 2" }
  }
}
